MANIFEST.in
README.md
setup.py
version.txt
auror_azkaban_jobtype_email/__init__.py
auror_azkaban_jobtype_email.egg-info/PKG-INFO
auror_azkaban_jobtype_email.egg-info/SOURCES.txt
auror_azkaban_jobtype_email.egg-info/dependency_links.txt
auror_azkaban_jobtype_email.egg-info/requires.txt
auror_azkaban_jobtype_email.egg-info/top_level.txt
auror_azkaban_jobtype_email/v1/__init__.py
auror_azkaban_jobtype_email/v1/job.py
auror_azkaban_jobtype_email/v2/__init__.py
auror_azkaban_jobtype_email/v2/job.py
tests/__init__.py
tests/unit/__init__.py
tests/unit/v1/__init__.py
tests/unit/v1/test_job.py
tests/unit/v2/__init__.py
tests/unit/v2/test_job.py