Metadata-Version: 1.0
Name: auror-azkaban-jobtype-email
Version: 0.0.1
Summary: Email jobtype for Azkaban Auror
Home-page: UNKNOWN
Author: Big Data
Author-email: bigdata@corp.globo.com
License: MIT
Platform: UNKNOWN
